mmcif_gen/__init__.py
mmcif_gen/investigation_engine.py
mmcif_gen/investigation_io.py
mmcif_gen/mmcif_gen.py
mmcif_gen/operations.py
mmcif_gen/facilities/__init__.py
mmcif_gen/facilities/crims.py
mmcif_gen/facilities/dls.py
mmcif_gen/facilities/esrf.py
mmcif_gen/facilities/maxiv.py
mmcif_gen/facilities/pdbe.py
mmcif_gen/facilities/xchem.py
mmcif_gen/test/__init__.py
mmcif_gen/test/test_operation.py
mmcif_gen/util/__init__.py
mmcif_gen/util/miss_importer.py
mmcif_gen/util/output_grabber.py
mmcif_gen-1.1.0.dist-info/METADATA
mmcif_gen-1.1.0.dist-info/WHEEL
mmcif_gen-1.1.0.dist-info/entry_points.txt
mmcif_gen-1.1.0.dist-info/top_level.txt
mmcif_gen-1.1.0.dist-info/RECORD
