Metadata-Version: 2.4
Name: mmcif_gen
Version: 1.1.0
Summary: CLI tool for creating mmCIF files from various facility data sources
Home-page: https://github.com/PDBeurope/Investigations/
Author: Syed Ahsan Tanweer
Author-email: ahsan@ebi.ac.uk
Project-URL: Bug Tracker, https://github.com/PDBeurope/Investigations/issues
Project-URL: Documentation, https://github.com/PDBeurope/Investigations/
Project-URL: Source Code, https://github.com/PDBeurope/Investigations/
Keywords: mmcif,crystallography,structural-biology,pdbe,synchrotron
Classifier: Programming Language :: Python :: 3
Classifier: Programming Language :: Python :: 3.6
Classifier: Programming Language :: Python :: 3.7
Classifier: Programming Language :: Python :: 3.8
Classifier: Programming Language :: Python :: 3.9
Classifier: License :: OSI Approved :: MIT License
Classifier: Operating System :: OS Independent
Classifier: Development Status :: 4 - Beta
Classifier: Intended Audience :: Science/Research
Classifier: Topic :: Scientific/Engineering :: Bio-Informatics
Requires-Python: >=3.6
Requires-Dist: argparse
Requires-Dist: gemmi
Requires-Dist: requests
Requires-Dist: jq
Dynamic: author
Dynamic: author-email
Dynamic: classifier
Dynamic: description
Dynamic: description-content-type
Dynamic: home-page
Dynamic: keywords
Dynamic: project-url
Dynamic: requires-dist
Dynamic: requires-python
Dynamic: summary
